blue_options/__init__.py
blue_options/__main__.py
blue_options/elapsed_timer.py
blue_options/timer.py
blue_options/urls.py
blue_options/.bash/alias.sh
blue_options/.bash/assert.sh
blue_options/.bash/blue_options.sh
blue_options/.bash/bool.sh
blue_options/.bash/browse.sh
blue_options/.bash/code.sh
blue_options/.bash/env.sh
blue_options/.bash/eval.sh
blue_options/.bash/generic_task.sh
blue_options/.bash/help.sh
blue_options/.bash/install.sh
blue_options/.bash/legacy.sh
blue_options/.bash/list.sh
blue_options/.bash/logging.sh
blue_options/.bash/open.sh
blue_options/.bash/options.sh
blue_options/.bash/pause.sh
blue_options/.bash/plugins.sh
blue_options/.bash/pylint.sh
blue_options/.bash/pytest.sh
blue_options/.bash/repeat.sh
blue_options/.bash/seed.sh
blue_options/.bash/sleep.sh
blue_options/.bash/source.sh
blue_options/.bash/string.sh
blue_options/.bash/terminal.sh
blue_options/.bash/test.sh
blue_options/.bash/wait.sh
blue_options/.bash/watch.sh
blue_options/.bash/env/backup.sh
blue_options/.bash/env/dot.sh
blue_options/.bash/env/dot/cat.sh
blue_options/.bash/env/dot/cp.sh
blue_options/.bash/env/dot/edit.sh
blue_options/.bash/env/dot/load.sh
blue_options/assets/example1.sh
blue_options/env/__init__.py
blue_options/env/functions.py
blue_options/help/__init__.py
blue_options/help/__main__.py
blue_options/help/functions.py
blue_options/help/parsing.py
blue_options/host/__init__.py
blue_options/host/__main__.py
blue_options/host/functions.py
blue_options/list/__init__.py
blue_options/list/__main__.py
blue_options/logger/__init__.py
blue_options/logger/config.py
blue_options/options/__init__.py
blue_options/options/__main__.py
blue_options/options/classes.py
blue_options/string/__init__.py
blue_options/string/__main__.py
blue_options/string/constants.py
blue_options/string/functions.py
blue_options/terminal/__init__.py
blue_options/terminal/__main__.py
blue_options/terminal/functions.py
blue_options-4.240.1.dist-info/LICENSE
blue_options-4.240.1.dist-info/METADATA
blue_options-4.240.1.dist-info/WHEEL
blue_options-4.240.1.dist-info/top_level.txt
blue_options-4.240.1.dist-info/RECORD
