Metadata-Version: 2.2
Name: blue_options
Version: 4.240.1
Summary: 🌀 options for Bash.
Home-page: https://github.com/kamangir/blue-options
Author: Arash Abadpour (Kamangir)
Author-email: arash@kamangir.net
License: Public Domain
Classifier: Programming Language :: Python :: 3
Classifier: Programming Language :: Unix Shell
Classifier: License :: Public Domain
Classifier: Operating System :: OS Independent
License-File: LICENSE
Requires-Dist: blueness
Requires-Dist: matplotlib
Requires-Dist: numpy
Requires-Dist: pymysql
Requires-Dist: pyyaml
Requires-Dist: pylint
Requires-Dist: pytest
Requires-Dist: python-dotenv[cli]
Requires-Dist: tqdm
Dynamic: author
Dynamic: author-email
Dynamic: classifier
Dynamic: description
Dynamic: description-content-type
Dynamic: home-page
Dynamic: license
Dynamic: requires-dist
Dynamic: summary
